paropy/__init__.py
paropy/coreproperties.py
paropy/data_utils.py
paropy/plot_utils.py
paropy/routines.py
paropy/data/CHAOS-7.7.mat
paropy/scripts/convective_power.py
paropy/scripts/diagnostic_parameters.py
paropy/scripts/diagnostics.py
paropy/scripts/differential_rotation.py
paropy/scripts/filter_surface_field.py
paropy/scripts/latitude_vs_Br.py
paropy/scripts/latitude_vs_Br_with_CHAOS.py
paropy/scripts/merdional_snapshot.py
paropy/scripts/meridional_snapshot.py
paropy/scripts/meridional_timeavg.py
paropy/scripts/meridional_timeavg_dark.py
paropy/scripts/rotation_rate.py
paropy/scripts/surface_snapshot.py
paropy/scripts/surface_timeavg.py
paropy-0.0.5.dist-info/LICENSE.md
paropy-0.0.5.dist-info/METADATA
paropy-0.0.5.dist-info/WHEEL
paropy-0.0.5.dist-info/top_level.txt
paropy-0.0.5.dist-info/RECORD
