Metadata-Version: 2.1
Name: paropy
Version: 0.0.5
Summary: Python package to process data from PARODY-JA4.3 dynamo simulations.
Home-page: https://github.com/jnywong/paropy
Author: Jenny Wong
Author-email: jenny.wong@univ-grenoble-alpes.fr
License: MIT
Platform: UNKNOWN
Requires-Dist: pytest
Requires-Dist: pandas
Requires-Dist: matplotlib
Requires-Dist: scipy
Requires-Dist: proj
Requires-Dist: pyshp
Requires-Dist: geos
Requires-Dist: shapely
Requires-Dist: cartopy
Requires-Dist: h5py
Requires-Dist: chaosmagpy
